README.md
nwon_django_seeding/__init__.py
nwon_django_seeding/actions/__init__.py
nwon_django_seeding/actions/load_seed_data.py
nwon_django_seeding/actions/load_seed_media_files.py
nwon_django_seeding/actions/write_database_seed_sets.py
nwon_django_seeding/actions/write_database_seeds.py
nwon_django_seeding/actions/write_storage_data_for_seeding.py
nwon_django_seeding/helper/__init__.py
nwon_django_seeding/helper/file_for_model_class.py
nwon_django_seeding/helper/load_seeds_from_file.py
nwon_django_seeding/helper/parse_info_from_seed_file_name.py
nwon_django_seeding/helper/set_key_to_none_in_seed_file.py
nwon_django_seeding/nwon_django_seeding_settings.py
nwon_django_seeding/seeding_running.py
nwon_django_seeding/typings.py
nwon_django_seeding-1.0.7.dist-info/METADATA
nwon_django_seeding-1.0.7.dist-info/WHEEL
nwon_django_seeding-1.0.7.dist-info/entry_points.txt
nwon_django_seeding-1.0.7.dist-info/RECORD
