Metadata-Version: 2.1
Name: nwon_django_seeding
Version: 1.0.7
Summary: A Django seeding solution build on top of fixtures
Home-page: https://nwon.de
License: MIT
Author: Reik Stiebeling
Author-email: reik.stiebeling@nwon.de
Requires-Python: >=3.8,<4.0
Classifier: License :: OSI Approved :: MIT License
Classifier: Programming Language :: Python :: 3
Classifier: Programming Language :: Python :: 3.8
Classifier: Programming Language :: Python :: 3.9
Classifier: Programming Language :: Python :: 3.10
Classifier: Programming Language :: Python :: 3.11
Classifier: Programming Language :: Python :: 3.12
Requires-Dist: boto3 (>=1.34.128,<2.0.0)
Requires-Dist: django (>=3.0)
Requires-Dist: nwon-baseline (>=0.2.15,<0.3.0)
Requires-Dist: nwon-django-toolbox (>=0.6.7,<0.7.0)
Requires-Dist: pydantic (>=2.1.0)
Project-URL: Repository, https://gitlab.com/nwon-group/nwon-tooling/pypi-packages/nwon-django-seeding.git
